main.py
treejson_cli-1.0.0.dist-info/METADATA
treejson_cli-1.0.0.dist-info/WHEEL
treejson_cli-1.0.0.dist-info/entry_points.txt
treejson_cli-1.0.0.dist-info/top_level.txt
treejson_cli-1.0.0.dist-info/RECORD
