Metadata-Version: 2.4
Name: treejson-cli
Version: 1.0.0
Summary: It shows the nested directory structure in JSON or YAML.
Author-email: masaniki <masaniki.software@gmail.com>
License-Expression: MIT
Project-URL: Repository, https://github.com/masaniki/python-treejson-cli
Project-URL: Document, https://github.com/masaniki/python-treejson-cli/blob/master/README.md
Project-URL: Issues, https://github.com/masaniki/python-treejson-cli/issues
Classifier: Development Status :: 1 - Planning
Classifier: Environment :: Console
Classifier: Topic :: Terminals
Classifier: Operating System :: OS Independent
Classifier: Programming Language :: Python :: 3
Classifier: Natural Language :: English
Classifier: Natural Language :: Japanese
Requires-Python: >=3.9
Requires-Dist: PyYAML
